generate_it/__init__.py
generate_it/__main__.py
generate_it/generator.py
generate_it/storage.py
generate_it/tui.py
generate_it/wordlist.txt
generate_it-0.2.0.dist-info/licenses/LICENSE
generate_it-0.2.0.dist-info/METADATA
generate_it-0.2.0.dist-info/WHEEL
generate_it-0.2.0.dist-info/entry_points.txt
generate_it-0.2.0.dist-info/top_level.txt
generate_it-0.2.0.dist-info/RECORD
