Metadata-Version: 2.4
Name: generate-it
Version: 0.2.0
Summary: Terminal credential generator with a curses-based TUI.
Author: j-kemble
License:                     GNU AFFERO GENERAL PUBLIC LICENSE
Project-URL: Homepage, https://github.com/j-kemble/Generate-It
Project-URL: Repository, https://github.com/j-kemble/Generate-It
Project-URL: Issues, https://github.com/j-kemble/Generate-It/issues
Keywords: password,passphrase,username,curses
Classifier: Development Status :: 3 - Alpha
Classifier: License :: OSI Approved :: GNU Affero General Public License v3 or later (AGPLv3+)
Classifier: Programming Language :: Python :: 3
Classifier: Programming Language :: Python :: 3 :: Only
Classifier: Operating System :: OS Independent
Classifier: Environment :: Console :: Curses
Classifier: Intended Audience :: End Users/Desktop
Classifier: Topic :: Utilities
Requires-Python: >=3.10
License-File: LICENSE
Requires-Dist: windows-curses; platform_system == "Windows"
Requires-Dist: platformdirs>=3.0.0
Requires-Dist: cryptography>=41.0.0
Requires-Dist: pyperclip>=1.8.0
Provides-Extra: test
Requires-Dist: pytest>=7; extra == "test"
Dynamic: license-file
